khmerpunctuate/__init__.py
khmerpunctuate/tagger.py
khmerpunctuate/tokenizer.json
khmerpunctuate/utils.py
tests/__init__.py
tests/tag.py
khmerpunctuate-0.2.0.dist-info/LICENSE
khmerpunctuate-0.2.0.dist-info/METADATA
khmerpunctuate-0.2.0.dist-info/WHEEL
khmerpunctuate-0.2.0.dist-info/top_level.txt
khmerpunctuate-0.2.0.dist-info/RECORD
