Metadata-Version: 2.1
Name: khmerpunctuate
Version: 0.2.0
Summary: Punctuation Restoration for Khmer language
Home-page: https://github.com/seanghay/khmerpunctuate
Author: Seanghay Yath
Author-email: seanghay.dev@gmail.com
License: MIT
Classifier: Programming Language :: Python :: 3
Classifier: Operating System :: OS Independent
Classifier: Intended Audience :: Developers
Classifier: Natural Language :: English
Requires-Python: >3.5
License-File: LICENSE
Requires-Dist: tokenizers
Requires-Dist: tqdm
Requires-Dist: onnxruntime
Requires-Dist: numpy
Requires-Dist: requests
Requires-Dist: appdirs
